setup.py
gleam.egg-info/PKG-INFO
gleam.egg-info/SOURCES.txt
gleam.egg-info/dependency_links.txt
gleam.egg-info/requires.txt
gleam.egg-info/top_level.txt
src/gleam/__init__.py
src/gleam/fields.py
src/gleam/panels.py
src/gleam/static/css/bootstrap-theme.css
src/gleam/static/css/bootstrap-theme.css.map
src/gleam/static/css/bootstrap-theme.min.css
src/gleam/static/css/bootstrap.css
src/gleam/static/css/bootstrap.css.map
src/gleam/static/css/bootstrap.min.css
src/gleam/static/css/styles.css
src/gleam/static/fonts/glyphicons-halflings-regular.eot
src/gleam/static/fonts/glyphicons-halflings-regular.svg
src/gleam/static/fonts/glyphicons-halflings-regular.ttf
src/gleam/static/fonts/glyphicons-halflings-regular.woff
src/gleam/static/images/ajax-loader.gif
src/gleam/static/js/bootstrap.js
src/gleam/static/js/bootstrap.min.js
src/gleam/static/js/jquery.form.js
src/gleam/static/js/jquery.min.js
src/gleam/templates/base.html
src/gleam/templates/content.html
src/gleam/templates/input.html
src/gleam/templates/macros.html
src/gleam/templates/overlay.html
src/gleam/templates/page.html
src/gleam/templates/plot.html
src/gleam/templates/tabs.html