Metadata-Version: 1.0
Name: gleam
Version: 0.1.2
Summary: Interactive visualization in Python
Home-page: UNKNOWN
Author: David Robinson
Author-email: dgrtwo@princeton.edu
License: UNKNOWN
Platform: UNKNOWN
